[{"date":"2010","enplaned":"x","deplaned":"x","domestic":"x","trans_border":"x","other_intl":"x"},{"date":"2011","enplaned":"x","deplaned":"x","domestic":"x","trans_border":"x","other_intl":"x"},{"date":"2012","enplaned":"x","deplaned":"x","domestic":"x","trans_border":"x","other_intl":"x"},{"date":"2013","enplaned":"x","deplaned":"x","domestic":"x","trans_border":"x","other_intl":"x"},{"date":"2014","enplaned":"x","deplaned":"x","domestic":"x","trans_border":"x","other_intl":"x"},{"date":"2015","enplaned":"x","deplaned":"x","domestic":"x","trans_border":"x","other_intl":"x"},{"date":"2016","enplaned":"160570","deplaned":"160570","domestic":"263925","trans_border":"x","other_intl":"x"},{"date":"2017","enplaned":"300937","deplaned":"300937","domestic":"549448","trans_border":"9968","other_intl":"40180"}]