[{"date":"2008","enplaned":"..","deplaned":".."},{"date":"2009","enplaned":"..","deplaned":".."},{"date":"2010","enplaned":"269370","deplaned":"269370"},{"date":"2011","enplaned":"278609","deplaned":"278609"},{"date":"2012","enplaned":"295285","deplaned":"295285"},{"date":"2013","enplaned":"324146","deplaned":"324146"},{"date":"2014","enplaned":"325544","deplaned":"325544"},{"date":"2015","enplaned":"315510","deplaned":"315510"},{"date":"2016","enplaned":"319506","deplaned":"319506"},{"date":"2017","enplaned":"324681","deplaned":"324681"}]