{
  "Canada": [
    {
      "target": 1,
      "source": 0,
      "value": 2914109
    },
    {
      "target": 2,
      "source": 0,
      "value": 773455
    },
    {
      "target": 3,
      "source": 0,
      "value": 5256929
    },
    {
      "target": 4,
      "source": 0,
      "value": 757706
    },
    {
      "target": 5,
      "source": 1,
      "value": 580605
    },
    {
      "target": 6,
      "source": 1,
      "value": 183852
    },
    {
      "target": 7,
      "source": 1,
      "value": 2149652
    },
    {
      "target": 8,
      "source": 2,
      "value": 636637
    },
    {
      "target": 9,
      "source": 2,
      "value": 29232
    },
    {
      "target": 10,
      "source": 2,
      "value": 107586
    },
    {
      "target": 11,
      "source": 3,
      "value": 557238
    },
    {
      "target": 12,
      "source": 3,
      "value": 35410
    },
    {
      "target": 13,
      "source": 3,
      "value": 4664281
    },
    {
      "target": 14,
      "source": 4,
      "value": 754993
    },
    {
      "target": 15,
      "source": 4,
      "value": 1741
    },
    {
      "target": 16,
      "source": 4,
      "value": 972
    },
    {
      "target": 17,
      "source": 7,
      "value": 1957952
    },
    {
      "target": 18,
      "source": 7,
      "value": 101876
    },
    {
      "target": 19,
      "source": 7,
      "value": 27367
    },
    {
      "target": 20,
      "source": 7,
      "value": 62457
    },
    {
      "target": 21,
      "source": 13,
      "value": 4525484
    },
    {
      "target": 22,
      "source": 13,
      "value": 82790
    },
    {
      "target": 23,
      "source": 13,
      "value": 4795
    },
    {
      "target": 24,
      "source": 13,
      "value": 51212
    }
  ],
  "Newfoundland and Labrador": [
    {
      "target": 1,
      "source": 0,
      "value": 5193
    },
    {
      "target": 2,
      "source": 0,
      "value": 5312
    },
    {
      "target": 3,
      "source": 0,
      "value": 2397
    },
    {
      "target": 4,
      "source": 0,
      "value": 7252
    },
    {
      "target": 5,
      "source": 1,
      "value": 4075
    },
    {
      "target": 6,
      "source": 1,
      "value": 1118
    },
    {
      "target": 7,
      "source": 1,
      "value": 0
    },
    {
      "target": 8,
      "source": 2,
      "value": 3948
    },
    {
      "target": 9,
      "source": 2,
      "value": 1364
    },
    {
      "target": 10,
      "source": 2,
      "value": 0
    },
    {
      "target": 11,
      "source": 3,
      "value": 2250
    },
    {
      "target": 12,
      "source": 3,
      "value": 147
    },
    {
      "target": 13,
      "source": 3,
      "value": 0
    },
    {
      "target": 14,
      "source": 4,
      "value": 5536
    },
    {
      "target": 15,
      "source": 4,
      "value": 1716
    },
    {
      "target": 16,
      "source": 4,
      "value": 0
    },
    {
      "target": 17,
      "source": 7,
      "value": 0
    },
    {
      "target": 18,
      "source": 7,
      "value": 0
    },
    {
      "target": 19,
      "source": 7,
      "value": 0
    },
    {
      "target": 20,
      "source": 7,
      "value": 0
    },
    {
      "target": 21,
      "source": 13,
      "value": 0
    },
    {
      "target": 22,
      "source": 13,
      "value": 0
    },
    {
      "target": 23,
      "source": 13,
      "value": 0
    },
    {
      "target": 24,
      "source": 13,
      "value": 0
    }
  ],
  "Prince Edward Island": [
    {
      "target": 1,
      "source": 0,
      "value": 949
    },
    {
      "target": 2,
      "source": 0,
      "value": 187
    },
    {
      "target": 3,
      "source": 0,
      "value": 106
    },
    {
      "target": 4,
      "source": 0,
      "value": 16
    },
    {
      "target": 5,
      "source": 1,
      "value": 949
    },
    {
      "target": 6,
      "source": 1,
      "value": 0
    },
    {
      "target": 7,
      "source": 1,
      "value": 0
    },
    {
      "target": 8,
      "source": 2,
      "value": 187
    },
    {
      "target": 9,
      "source": 2,
      "value": 0
    },
    {
      "target": 10,
      "source": 2,
      "value": 0
    },
    {
      "target": 11,
      "source": 3,
      "value": 101
    },
    {
      "target": 12,
      "source": 3,
      "value": 5
    },
    {
      "target": 13,
      "source": 3,
      "value": 0
    },
    {
      "target": 14,
      "source": 4,
      "value": 16
    },
    {
      "target": 15,
      "source": 4,
      "value": 0
    },
    {
      "target": 16,
      "source": 4,
      "value": 0
    },
    {
      "target": 17,
      "source": 7,
      "value": 0
    },
    {
      "target": 18,
      "source": 7,
      "value": 0
    },
    {
      "target": 19,
      "source": 7,
      "value": 0
    },
    {
      "target": 20,
      "source": 7,
      "value": 0
    },
    {
      "target": 21,
      "source": 13,
      "value": 0
    },
    {
      "target": 22,
      "source": 13,
      "value": 0
    },
    {
      "target": 23,
      "source": 13,
      "value": 0
    },
    {
      "target": 24,
      "source": 13,
      "value": 0
    }
  ],
  "Nova Scotia": [
    {
      "target": 1,
      "source": 0,
      "value": 22372
    },
    {
      "target": 2,
      "source": 0,
      "value": 9629
    },
    {
      "target": 3,
      "source": 0,
      "value": 7850
    },
    {
      "target": 4,
      "source": 0,
      "value": 5791
    },
    {
      "target": 5,
      "source": 1,
      "value": 12353
    },
    {
      "target": 6,
      "source": 1,
      "value": 4609
    },
    {
      "target": 7,
      "source": 1,
      "value": 5410
    },
    {
      "target": 8,
      "source": 2,
      "value": 8683
    },
    {
      "target": 9,
      "source": 2,
      "value": 883
    },
    {
      "target": 10,
      "source": 2,
      "value": 63
    },
    {
      "target": 11,
      "source": 3,
      "value": 5500
    },
    {
      "target": 12,
      "source": 3,
      "value": 544
    },
    {
      "target": 13,
      "source": 3,
      "value": 1806
    },
    {
      "target": 14,
      "source": 4,
      "value": 5767
    },
    {
      "target": 15,
      "source": 4,
      "value": 24
    },
    {
      "target": 16,
      "source": 4,
      "value": 0
    },
    {
      "target": 17,
      "source": 7,
      "value": 4443
    },
    {
      "target": 18,
      "source": 7,
      "value": 130
    },
    {
      "target": 19,
      "source": 7,
      "value": 0
    },
    {
      "target": 20,
      "source": 7,
      "value": 837
    },
    {
      "target": 21,
      "source": 13,
      "value": 1542
    },
    {
      "target": 22,
      "source": 13,
      "value": 0
    },
    {
      "target": 23,
      "source": 13,
      "value": 0
    },
    {
      "target": 24,
      "source": 13,
      "value": 264
    }
  ],
  "New Brunswick": [
    {
      "target": 1,
      "source": 0,
      "value": 112872
    },
    {
      "target": 2,
      "source": 0,
      "value": 930
    },
    {
      "target": 3,
      "source": 0,
      "value": 335223
    },
    {
      "target": 4,
      "source": 0,
      "value": 95
    },
    {
      "target": 5,
      "source": 1,
      "value": 980
    },
    {
      "target": 6,
      "source": 1,
      "value": 189
    },
    {
      "target": 7,
      "source": 1,
      "value": 111703
    },
    {
      "target": 8,
      "source": 2,
      "value": 101
    },
    {
      "target": 9,
      "source": 2,
      "value": 0
    },
    {
      "target": 10,
      "source": 2,
      "value": 829
    },
    {
      "target": 11,
      "source": 3,
      "value": 576
    },
    {
      "target": 12,
      "source": 3,
      "value": 102
    },
    {
      "target": 13,
      "source": 3,
      "value": 334545
    },
    {
      "target": 14,
      "source": 4,
      "value": 95
    },
    {
      "target": 15,
      "source": 4,
      "value": 0
    },
    {
      "target": 16,
      "source": 4,
      "value": 0
    },
    {
      "target": 17,
      "source": 7,
      "value": 109355
    },
    {
      "target": 18,
      "source": 7,
      "value": 797
    },
    {
      "target": 19,
      "source": 7,
      "value": 0
    },
    {
      "target": 20,
      "source": 7,
      "value": 1551
    },
    {
      "target": 21,
      "source": 13,
      "value": 329714
    },
    {
      "target": 22,
      "source": 13,
      "value": 1572
    },
    {
      "target": 23,
      "source": 13,
      "value": 0
    },
    {
      "target": 24,
      "source": 13,
      "value": 3259
    }
  ],
  "Quebec": [
    {
      "target": 1,
      "source": 0,
      "value": 281021
    },
    {
      "target": 2,
      "source": 0,
      "value": 140849
    },
    {
      "target": 3,
      "source": 0,
      "value": 744648
    },
    {
      "target": 4,
      "source": 0,
      "value": 187076
    },
    {
      "target": 5,
      "source": 1,
      "value": 81349
    },
    {
      "target": 6,
      "source": 1,
      "value": 454
    },
    {
      "target": 7,
      "source": 1,
      "value": 199218
    },
    {
      "target": 8,
      "source": 2,
      "value": 124612
    },
    {
      "target": 9,
      "source": 2,
      "value": 53
    },
    {
      "target": 10,
      "source": 2,
      "value": 16184
    },
    {
      "target": 11,
      "source": 3,
      "value": 78860
    },
    {
      "target": 12,
      "source": 3,
      "value": 3101
    },
    {
      "target": 13,
      "source": 3,
      "value": 662687
    },
    {
      "target": 14,
      "source": 4,
      "value": 187075
    },
    {
      "target": 15,
      "source": 4,
      "value": 1
    },
    {
      "target": 16,
      "source": 4,
      "value": 0
    },
    {
      "target": 17,
      "source": 7,
      "value": 183048
    },
    {
      "target": 18,
      "source": 7,
      "value": 12693
    },
    {
      "target": 19,
      "source": 7,
      "value": 2334
    },
    {
      "target": 20,
      "source": 7,
      "value": 1143
    },
    {
      "target": 21,
      "source": 13,
      "value": 631134
    },
    {
      "target": 22,
      "source": 13,
      "value": 19011
    },
    {
      "target": 23,
      "source": 13,
      "value": 1613
    },
    {
      "target": 24,
      "source": 13,
      "value": 10929
    }
  ],
  "Ontario": [
    {
      "target": 1,
      "source": 0,
      "value": 1530522
    },
    {
      "target": 2,
      "source": 0,
      "value": 312122
    },
    {
      "target": 3,
      "source": 0,
      "value": 2277539
    },
    {
      "target": 4,
      "source": 0,
      "value": 389657
    },
    {
      "target": 5,
      "source": 1,
      "value": 241752
    },
    {
      "target": 6,
      "source": 1,
      "value": 27421
    },
    {
      "target": 7,
      "source": 1,
      "value": 1261349
    },
    {
      "target": 8,
      "source": 2,
      "value": 272700
    },
    {
      "target": 9,
      "source": 2,
      "value": 88
    },
    {
      "target": 10,
      "source": 2,
      "value": 39334
    },
    {
      "target": 11,
      "source": 3,
      "value": 270506
    },
    {
      "target": 12,
      "source": 3,
      "value": 10452
    },
    {
      "target": 13,
      "source": 3,
      "value": 1996581
    },
    {
      "target": 14,
      "source": 4,
      "value": 389657
    },
    {
      "target": 15,
      "source": 4,
      "value": 0
    },
    {
      "target": 16,
      "source": 4,
      "value": 0
    },
    {
      "target": 17,
      "source": 7,
      "value": 1185976
    },
    {
      "target": 18,
      "source": 7,
      "value": 47644
    },
    {
      "target": 19,
      "source": 7,
      "value": 1135
    },
    {
      "target": 20,
      "source": 7,
      "value": 26594
    },
    {
      "target": 21,
      "source": 13,
      "value": 1939211
    },
    {
      "target": 22,
      "source": 13,
      "value": 40923
    },
    {
      "target": 23,
      "source": 13,
      "value": 513
    },
    {
      "target": 24,
      "source": 13,
      "value": 15934
    }
  ],
  "Manitoba": [
    {
      "target": 1,
      "source": 0,
      "value": 46738
    },
    {
      "target": 2,
      "source": 0,
      "value": 1531
    },
    {
      "target": 3,
      "source": 0,
      "value": 162740
    },
    {
      "target": 4,
      "source": 0,
      "value": 1372
    },
    {
      "target": 5,
      "source": 1,
      "value": 9331
    },
    {
      "target": 6,
      "source": 1,
      "value": 0
    },
    {
      "target": 7,
      "source": 1,
      "value": 37407
    },
    {
      "target": 8,
      "source": 2,
      "value": 1125
    },
    {
      "target": 9,
      "source": 2,
      "value": 0
    },
    {
      "target": 10,
      "source": 2,
      "value": 406
    },
    {
      "target": 11,
      "source": 3,
      "value": 7884
    },
    {
      "target": 12,
      "source": 3,
      "value": 0
    },
    {
      "target": 13,
      "source": 3,
      "value": 154856
    },
    {
      "target": 14,
      "source": 4,
      "value": 1372
    },
    {
      "target": 15,
      "source": 4,
      "value": 0
    },
    {
      "target": 16,
      "source": 4,
      "value": 0
    },
    {
      "target": 17,
      "source": 7,
      "value": 36557
    },
    {
      "target": 18,
      "source": 7,
      "value": 668
    },
    {
      "target": 19,
      "source": 7,
      "value": 0
    },
    {
      "target": 20,
      "source": 7,
      "value": 182
    },
    {
      "target": 21,
      "source": 13,
      "value": 151719
    },
    {
      "target": 22,
      "source": 13,
      "value": 2235
    },
    {
      "target": 23,
      "source": 13,
      "value": 0
    },
    {
      "target": 24,
      "source": 13,
      "value": 902
    }
  ],
  "Saskatchewan": [
    {
      "target": 1,
      "source": 0,
      "value": 18562
    },
    {
      "target": 2,
      "source": 0,
      "value": 783
    },
    {
      "target": 3,
      "source": 0,
      "value": 51707
    },
    {
      "target": 4,
      "source": 0,
      "value": 1174
    },
    {
      "target": 5,
      "source": 1,
      "value": 6385
    },
    {
      "target": 6,
      "source": 1,
      "value": 0
    },
    {
      "target": 7,
      "source": 1,
      "value": 12177
    },
    {
      "target": 8,
      "source": 2,
      "value": 631
    },
    {
      "target": 9,
      "source": 2,
      "value": 0
    },
    {
      "target": 10,
      "source": 2,
      "value": 152
    },
    {
      "target": 11,
      "source": 3,
      "value": 7939
    },
    {
      "target": 12,
      "source": 3,
      "value": 0
    },
    {
      "target": 13,
      "source": 3,
      "value": 43768
    },
    {
      "target": 14,
      "source": 4,
      "value": 1174
    },
    {
      "target": 15,
      "source": 4,
      "value": 0
    },
    {
      "target": 16,
      "source": 4,
      "value": 0
    },
    {
      "target": 17,
      "source": 7,
      "value": 11777
    },
    {
      "target": 18,
      "source": 7,
      "value": 298
    },
    {
      "target": 19,
      "source": 7,
      "value": 0
    },
    {
      "target": 20,
      "source": 7,
      "value": 102
    },
    {
      "target": 21,
      "source": 13,
      "value": 42637
    },
    {
      "target": 22,
      "source": 13,
      "value": 279
    },
    {
      "target": 23,
      "source": 13,
      "value": 0
    },
    {
      "target": 24,
      "source": 13,
      "value": 852
    }
  ],
  "Alberta": [
    {
      "target": 1,
      "source": 0,
      "value": 121539
    },
    {
      "target": 2,
      "source": 0,
      "value": 45865
    },
    {
      "target": 3,
      "source": 0,
      "value": 183309
    },
    {
      "target": 4,
      "source": 0,
      "value": 57486
    },
    {
      "target": 5,
      "source": 1,
      "value": 75109
    },
    {
      "target": 6,
      "source": 1,
      "value": 0
    },
    {
      "target": 7,
      "source": 1,
      "value": 46430
    },
    {
      "target": 8,
      "source": 2,
      "value": 44214
    },
    {
      "target": 9,
      "source": 2,
      "value": 0
    },
    {
      "target": 10,
      "source": 2,
      "value": 1651
    },
    {
      "target": 11,
      "source": 3,
      "value": 99441
    },
    {
      "target": 12,
      "source": 3,
      "value": 0
    },
    {
      "target": 13,
      "source": 3,
      "value": 83868
    },
    {
      "target": 14,
      "source": 4,
      "value": 57486
    },
    {
      "target": 15,
      "source": 4,
      "value": 0
    },
    {
      "target": 16,
      "source": 4,
      "value": 0
    },
    {
      "target": 17,
      "source": 7,
      "value": 43581
    },
    {
      "target": 18,
      "source": 7,
      "value": 2261
    },
    {
      "target": 19,
      "source": 7,
      "value": 0
    },
    {
      "target": 20,
      "source": 7,
      "value": 588
    },
    {
      "target": 21,
      "source": 13,
      "value": 81625
    },
    {
      "target": 22,
      "source": 13,
      "value": 935
    },
    {
      "target": 23,
      "source": 13,
      "value": 0
    },
    {
      "target": 24,
      "source": 13,
      "value": 1308
    }
  ],
  "British Columbia": [
    {
      "target": 1,
      "source": 0,
      "value": 703547
    },
    {
      "target": 2,
      "source": 0,
      "value": 245619
    },
    {
      "target": 3,
      "source": 0,
      "value": 1475718
    },
    {
      "target": 4,
      "source": 0,
      "value": 107565
    },
    {
      "target": 5,
      "source": 1,
      "value": 146249
    },
    {
      "target": 6,
      "source": 1,
      "value": 150061
    },
    {
      "target": 7,
      "source": 1,
      "value": 407237
    },
    {
      "target": 8,
      "source": 2,
      "value": 179212
    },
    {
      "target": 9,
      "source": 2,
      "value": 26786
    },
    {
      "target": 10,
      "source": 2,
      "value": 39621
    },
    {
      "target": 11,
      "source": 3,
      "value": 83694
    },
    {
      "target": 12,
      "source": 3,
      "value": 21059
    },
    {
      "target": 13,
      "source": 3,
      "value": 1370965
    },
    {
      "target": 14,
      "source": 4,
      "value": 106593
    },
    {
      "target": 15,
      "source": 4,
      "value": 0
    },
    {
      "target": 16,
      "source": 4,
      "value": 972
    },
    {
      "target": 17,
      "source": 7,
      "value": 358117
    },
    {
      "target": 18,
      "source": 7,
      "value": 12426
    },
    {
      "target": 19,
      "source": 7,
      "value": 6377
    },
    {
      "target": 20,
      "source": 7,
      "value": 30317
    },
    {
      "target": 21,
      "source": 13,
      "value": 1337056
    },
    {
      "target": 22,
      "source": 13,
      "value": 14554
    },
    {
      "target": 23,
      "source": 13,
      "value": 1812
    },
    {
      "target": 24,
      "source": 13,
      "value": 17543
    }
  ],
  "Yukon": [
    {
      "target": 1,
      "source": 0,
      "value": 70666
    },
    {
      "target": 2,
      "source": 0,
      "value": 10400
    },
    {
      "target": 3,
      "source": 0,
      "value": 15652
    },
    {
      "target": 4,
      "source": 0,
      "value": 78
    },
    {
      "target": 5,
      "source": 1,
      "value": 1945
    },
    {
      "target": 6,
      "source": 1,
      "value": 0
    },
    {
      "target": 7,
      "source": 1,
      "value": 68721
    },
    {
      "target": 8,
      "source": 2,
      "value": 1054
    },
    {
      "target": 9,
      "source": 2,
      "value": 0
    },
    {
      "target": 10,
      "source": 2,
      "value": 9346
    },
    {
      "target": 11,
      "source": 3,
      "value": 447
    },
    {
      "target": 12,
      "source": 3,
      "value": 0
    },
    {
      "target": 13,
      "source": 3,
      "value": 15205
    },
    {
      "target": 14,
      "source": 4,
      "value": 78
    },
    {
      "target": 15,
      "source": 4,
      "value": 0
    },
    {
      "target": 16,
      "source": 4,
      "value": 0
    },
    {
      "target": 17,
      "source": 7,
      "value": 25098
    },
    {
      "target": 18,
      "source": 7,
      "value": 24959
    },
    {
      "target": 19,
      "source": 7,
      "value": 17521
    },
    {
      "target": 20,
      "source": 7,
      "value": 1143
    },
    {
      "target": 21,
      "source": 13,
      "value": 10846
    },
    {
      "target": 22,
      "source": 13,
      "value": 3281
    },
    {
      "target": 23,
      "source": 13,
      "value": 857
    },
    {
      "target": 24,
      "source": 13,
      "value": 221
    }
  ],
  "Nunavut": [
    {
      "target": 1,
      "source": 0,
      "value": 128
    },
    {
      "target": 2,
      "source": 0,
      "value": 228
    },
    {
      "target": 3,
      "source": 0,
      "value": 40
    },
    {
      "target": 4,
      "source": 0,
      "value": 144
    },
    {
      "target": 5,
      "source": 1,
      "value": 128
    },
    {
      "target": 6,
      "source": 1,
      "value": 0
    },
    {
      "target": 7,
      "source": 1,
      "value": ".."
    },
    {
      "target": 8,
      "source": 2,
      "value": 170
    },
    {
      "target": 9,
      "source": 2,
      "value": 58
    },
    {
      "target": 10,
      "source": 2,
      "value": ".."
    },
    {
      "target": 11,
      "source": 3,
      "value": 40
    },
    {
      "target": 12,
      "source": 3,
      "value": 0
    },
    {
      "target": 13,
      "source": 3,
      "value": ".."
    },
    {
      "target": 14,
      "source": 4,
      "value": 144
    },
    {
      "target": 15,
      "source": 4,
      "value": 0
    },
    {
      "target": 16,
      "source": 4,
      "value": ".."
    },
    {
      "target": 17,
      "source": 7,
      "value": ".."
    },
    {
      "target": 18,
      "source": 7,
      "value": ".."
    },
    {
      "target": 19,
      "source": 7,
      "value": ".."
    },
    {
      "target": 20,
      "source": 7,
      "value": 0
    },
    {
      "target": 21,
      "source": 13,
      "value": ".."
    },
    {
      "target": 22,
      "source": 13,
      "value": ".."
    },
    {
      "target": 23,
      "source": 13,
      "value": ".."
    },
    {
      "target": 24,
      "source": 13,
      "value": 0
    }
  ],
  "nodes": [
    {
      "node": 0,
      "name": "intl"
    },
    {
      "node": 1,
      "name": "USres"
    },
    {
      "node": 2,
      "name": "nonUSres"
    },
    {
      "node": 3,
      "name": "cdnFromUS"
    },
    {
      "node": 4,
      "name": "cdnFromOther"
    },
    {
      "node": 5,
      "name": "USres_air"
    },
    {
      "node": 6,
      "name": "USres_marine"
    },
    {
      "node": 7,
      "name": "USres_land"
    },
    {
      "node": 8,
      "name": "nonUSres_air"
    },
    {
      "node": 9,
      "name": "nonUSres_marine"
    },
    {
      "node": 10,
      "name": "nonUSres_land"
    },
    {
      "node": 11,
      "name": "cdnFromUS_air"
    },
    {
      "node": 12,
      "name": "cdnFromUS_marine"
    },
    {
      "node": 13,
      "name": "cdnFromUS_land"
    },
    {
      "node": 14,
      "name": "cdnFromOther_air"
    },
    {
      "node": 15,
      "name": "cdnFromOther_marine"
    },
    {
      "node": 16,
      "name": "cdnFromOther_land"
    },
    {
      "node": 17,
      "name": "USres_car"
    },
    {
      "node": 18,
      "name": "USres_bus"
    },
    {
      "node": 19,
      "name": "USres_train"
    },
    {
      "node": 20,
      "name": "USres_other"
    },
    {
      "node": 21,
      "name": "cdnFromUS_car"
    },
    {
      "node": 22,
      "name": "cdnFromUS_bus"
    },
    {
      "node": 23,
      "name": "cdnFromUS_train"
    },
    {
      "node": 24,
      "name": "cdnFromUS_other"
    }
  ]
}