{
  "2010": {
    "All": 648902,
    "AT": 648902,
    "QC": 0,
    "ON": 0,
    "MB": 0,
    "SK": 0,
    "AB": 0,
    "BC": 0,
    "USA-MX": 0
  },
  "2011": {
    "All": 690367,
    "AT": 690367,
    "QC": 0,
    "ON": 0,
    "MB": 0,
    "SK": 0,
    "AB": 0,
    "BC": 0,
    "USA-MX": 0
  },
  "2012": {
    "All": 669653,
    "AT": 669653,
    "QC": 0,
    "ON": 0,
    "MB": 0,
    "SK": 0,
    "AB": 0,
    "BC": 0,
    "USA-MX": 0
  },
  "2013": {
    "All": 658186,
    "AT": 658186,
    "QC": 0,
    "ON": 0,
    "MB": 0,
    "SK": 0,
    "AB": 0,
    "BC": 0,
    "USA-MX": 0
  },
  "2014": {
    "All": 563291,
    "AT": 563291,
    "QC": 0,
    "ON": 0,
    "MB": 0,
    "SK": 0,
    "AB": 0,
    "BC": 0,
    "USA-MX": 0
  },
  "2015": {
    "All": 639539,
    "AT": 639539,
    "QC": 0,
    "ON": 0,
    "MB": 0,
    "SK": 0,
    "AB": 0,
    "BC": 0,
    "USA-MX": 0
  },
  "2016": {
    "All": 8580,
    "AT": 8580,
    "QC": 0,
    "ON": 0,
    "MB": 0,
    "SK": 0,
    "AB": 0,
    "BC": 0,
    "USA-MX": 0
  },
  "2017": {
    "All": 0,
    "AT": 0,
    "QC": 0,
    "ON": 0,
    "MB": 0,
    "SK": 0,
    "AB": 0,
    "BC": 0,
    "USA-MX": 0
  }
}